reflexia/__init__.py
reflexia/account.py
reflexia/client.py
reflexia/epistemic.py
reflexia/exceptions.py
reflexia/field.py
reflexia/patterns.py
reflexia/payment.py
reflexia-0.1.0.dist-info/licenses/LICENSE
reflexia-0.1.0.dist-info/METADATA
reflexia-0.1.0.dist-info/WHEEL
reflexia-0.1.0.dist-info/top_level.txt
reflexia-0.1.0.dist-info/RECORD
