Metadata-Version: 2.4
Name: reflexia
Version: 0.1.0
Summary: Python SDK for Reflexia API - Quantum Coordination Infrastructure for Autonomous Agent Swarms
Author-email: Reflexia <support@reflexia.dev>
License: MIT
Project-URL: Homepage, https://reflexia.dev
Project-URL: Documentation, https://reflexia.dev/docs
Project-URL: Repository, https://github.com/AaronVick/reflexia-python-sdk
Project-URL: Issues, https://github.com/AaronVick/reflexia-python-sdk/issues
Keywords: reflexia,api,sdk,agents,coordination,swarm
Classifier: Development Status :: 3 - Alpha
Classifier: Intended Audience :: Developers
Classifier: License :: OSI Approved :: MIT License
Classifier: Programming Language :: Python :: 3
Classifier: Programming Language :: Python :: 3.8
Classifier: Programming Language :: Python :: 3.9
Classifier: Programming Language :: Python :: 3.10
Classifier: Programming Language :: Python :: 3.11
Classifier: Programming Language :: Python :: 3.12
Classifier: Topic :: Software Development :: Libraries :: Python Modules
Requires-Python: >=3.8
License-File: LICENSE
Requires-Dist: requests>=2.28.0
Requires-Dist: typing-extensions>=4.0.0; python_version < "3.10"
Provides-Extra: dev
Requires-Dist: pytest>=7.0.0; extra == "dev"
Requires-Dist: pytest-cov>=4.0.0; extra == "dev"
Requires-Dist: pytest-mock>=3.10.0; extra == "dev"
Requires-Dist: black>=23.0.0; extra == "dev"
Requires-Dist: mypy>=1.0.0; extra == "dev"
Requires-Dist: ruff>=0.1.0; extra == "dev"
Dynamic: license-file
